{
  "datastatuskuliah": [
    {
      "id_smt": "20221",
      "sks_smt": 20,
      "nm_stat_mhs": "Aktif"
    },
    {
      "id_smt": "20222",
      "sks_smt": 21,
      "nm_stat_mhs": "Aktif"
    },
    {
      "id_smt": "20231",
      "sks_smt": 23,
      "nm_stat_mhs": "Aktif"
    }
  ],
  "datastudi": [
    {
      "kode_mk": "DAF01",
      "nm_mk": "DASAR NUTRISI TERNAK",
      "sks_mk": 2,
      "id_smt": "20221",
      "nilai_huruf": null
    },
    {
      "kode_mk": "DAU01",
      "nm_mk": "FITRAH BERAGAMA",
      "sks_mk": 1,
      "id_smt": "20221",
      "nilai_huruf": null
    },
    {
      "kode_mk": "DAU09",
      "nm_mk": "BAHASA INDONESIA",
      "sks_mk": 2,
      "id_smt": "20221",
      "nilai_huruf": null
    },
    {
      "kode_mk": "DAK03",
      "nm_mk": "GENETIKA",
      "sks_mk": 3,
      "id_smt": "20221",
      "nilai_huruf": null
    },
    {
      "kode_mk": "DAF02",
      "nm_mk": "STATISTIKA DIGITAL",
      "sks_mk": 3,
      "id_smt": "20221",
      "nilai_huruf": null
    },
    {
      "kode_mk": "DAK01",
      "nm_mk": "BIOKIMIA TERNAK",
      "sks_mk": 3,
      "id_smt": "20221",
      "nilai_huruf": null
    },
    {
      "kode_mk": "DAK02",
      "nm_mk": "MIKROBIOLOGI",
      "sks_mk": 3,
      "id_smt": "20221",
      "nilai_huruf": null
    },
    {
      "kode_mk": "DAU07",
      "nm_mk": "PANCASILA",
      "sks_mk": 2,
      "id_smt": "20221",
      "nilai_huruf": null
    },
    {
      "kode_mk": "DAU02",
      "nm_mk": "AQIDAH ASWAJA",
      "sks_mk": 1,
      "id_smt": "20221",
      "nilai_huruf": null
    },
    {
      "kode_mk": "DAU10",
      "nm_mk": "BAHASA INGGRIS",
      "sks_mk": 2,
      "id_smt": "20222",
      "nilai_huruf": null
    },
    {
      "kode_mk": "DAU03",
      "nm_mk": "AMALIAH ASWAJA",
      "sks_mk": 1,
      "id_smt": "20222",
      "nilai_huruf": null
    },
    {
      "kode_mk": "DAF04",
      "nm_mk": "ANATOMI DAN FISIOLOGI TERNAK",
      "sks_mk": 3,
      "id_smt": "20222",
      "nilai_huruf": null
    },
    {
      "kode_mk": "DAF03",
      "nm_mk": "PENULISAN KARYA ILMIAH DAN TEKNIK SEMINAR",
      "sks_mk": 3,
      "id_smt": "20222",
      "nilai_huruf": null
    },
    {
      "kode_mk": "DAU08",
      "nm_mk": "KEWARGANEGARAAN",
      "sks_mk": 2,
      "id_smt": "20222",
      "nilai_huruf": null
    },
    {
      "kode_mk": "DAU04",
      "nm_mk": "AKHLAK DAN TASAWUF",
      "sks_mk": 1,
      "id_smt": "20222",
      "nilai_huruf": null
    },
    {
      "kode_mk": "DAK34",
      "nm_mk": "EKONOMI BISNIS PETERNAKAN",
      "sks_mk": 3,
      "id_smt": "20222",
      "nilai_huruf": null
    },
    {
      "kode_mk": "DAK04",
      "nm_mk": "BAHAN DAN FORMULASI PAKAN TERNAK",
      "sks_mk": 3,
      "id_smt": "20222",
      "nilai_huruf": null
    },
    {
      "kode_mk": "DAK06",
      "nm_mk": "ILMU PRODUKSI ANEKA TERNAK",
      "sks_mk": 3,
      "id_smt": "20222",
      "nilai_huruf": null
    },
    {
      "kode_mk": "DAK10",
      "nm_mk": "ILMU PRODUKSI TERNAK UNGGAS",
      "sks_mk": 3,
      "id_smt": "20231",
      "nilai_huruf": null
    },
    {
      "kode_mk": "DAK08",
      "nm_mk": "ANIMAL BREEDING",
      "sks_mk": 2,
      "id_smt": "20231",
      "nilai_huruf": null
    },
    {
      "kode_mk": "DAK07",
      "nm_mk": "ILMU PRODUKSI TERNAK POTONG",
      "sks_mk": 3,
      "id_smt": "20231",
      "nilai_huruf": null
    },
    {
      "kode_mk": "DAF07",
      "nm_mk": "DASAR TEKNOLOGI HASIL TERNAK",
      "sks_mk": 2,
      "id_smt": "20231",
      "nilai_huruf": null
    },
    {
      "kode_mk": "DAK21",
      "nm_mk": "ILMU KESEHATAN TERNAK",
      "sks_mk": 3,
      "id_smt": "20231",
      "nilai_huruf": null
    },
    {
      "kode_mk": "DAK11",
      "nm_mk": "ILMU REPRODUKSI TERNAK",
      "sks_mk": 3,
      "id_smt": "20231",
      "nilai_huruf": null
    },
    {
      "kode_mk": "DAU11",
      "nm_mk": "ENTREPRENEURSHIP",
      "sks_mk": 3,
      "id_smt": "20231",
      "nilai_huruf": null
    },
    {
      "kode_mk": "DAK09",
      "nm_mk": "ILMU PRODUKSI TERNAK PERAH",
      "sks_mk": 3,
      "id_smt": "20231",
      "nilai_huruf": null
    },
    {
      "kode_mk": "DAU05",
      "nm_mk": "ASWAJA AN NAHDLIYAH",
      "sks_mk": 1,
      "id_smt": "20231",
      "nilai_huruf": null
    }
  ],
  "dataumum": {
    "nm_pd": "MUHAMMAD JIBRIL ADRIANSYAH",
    "jk": "L",
    "nipd": "22201041045",
    "namapt": "Universitas Islam Malang",
    "namajenjang": "S1",
    "namaprodi": "Peternakan",
    "reg_pd": "667C8C5C-27D9-47AA-B8E5-EA556AFE77DF",
    "mulai_smt": "20221",
    "nm_jns_daftar": "Peserta didik baru",
    "nm_pt_asal": null,
    "nm_prodi_asal": null,
    "ket_keluar": null,
    "tgl_keluar": null,
    "no_seri_ijazah": null,
    "sert_prof": null,
    "link_pt": "/data_pt/RjVDODhGREUtRTlGRS00MTY2LTg2MjktOUFEREZFQUJEQzJF",
    "link_prodi": "/data_prodi/RUJBRDQ2RjEtQThGNi00Q0I4LTgxMzMtQUM2OTgzQUVFRDA4"
  }
}