{
  "datastatuskuliah": [
    {
      "id_smt": "20231",
      "sks_smt": 22,
      "nm_stat_mhs": "Aktif"
    }
  ],
  "datastudi": [
    {
      "kode_mk": "DAK6402",
      "nm_mk": "Akuntansi Pengantar",
      "sks_mk": 4,
      "id_smt": "20231",
      "nilai_huruf": null
    },
    {
      "kode_mk": "DAK6229",
      "nm_mk": "Perpajakan",
      "sks_mk": 2,
      "id_smt": "20231",
      "nilai_huruf": null
    },
    {
      "kode_mk": "DAK6255",
      "nm_mk": "Hukum Bisnis",
      "sks_mk": 2,
      "id_smt": "20231",
      "nilai_huruf": null
    },
    {
      "kode_mk": "DAK6231",
      "nm_mk": "Komputer Akuntansi",
      "sks_mk": 2,
      "id_smt": "20231",
      "nilai_huruf": null
    },
    {
      "kode_mk": "FEK6204",
      "nm_mk": "Pengantar Manajemen",
      "sks_mk": 2,
      "id_smt": "20231",
      "nilai_huruf": null
    },
    {
      "kode_mk": "MKU6209",
      "nm_mk": "Bahasa Indonesia",
      "sks_mk": 2,
      "id_smt": "20231",
      "nilai_huruf": null
    },
    {
      "kode_mk": "MKU6217",
      "nm_mk": "Literasi Sains dan Teknologi**)",
      "sks_mk": 2,
      "id_smt": "20231",
      "nilai_huruf": null
    },
    {
      "kode_mk": "MKU6208",
      "nm_mk": "Pancasila",
      "sks_mk": 2,
      "id_smt": "20231",
      "nilai_huruf": null
    },
    {
      "kode_mk": "DAK6228",
      "nm_mk": "Bank dan Lembaga Keuangan Non Bank",
      "sks_mk": 2,
      "id_smt": "20231",
      "nilai_huruf": null
    },
    {
      "kode_mk": "MKU6211",
      "nm_mk": "Bahasa Inggris",
      "sks_mk": 2,
      "id_smt": "20231",
      "nilai_huruf": null
    }
  ],
  "dataumum": {
    "nm_pd": "NESYA LAKSITA DEWI",
    "jk": "P",
    "nipd": "23091220089",
    "namapt": "Universitas Negeri Yogyakarta",
    "namajenjang": "D4",
    "namaprodi": "Akuntansi",
    "reg_pd": "D120D62C-D856-4F99-86B4-59152E628B7E",
    "mulai_smt": "20231",
    "nm_jns_daftar": "Peserta didik baru",
    "nm_pt_asal": null,
    "nm_prodi_asal": null,
    "ket_keluar": null,
    "tgl_keluar": null,
    "no_seri_ijazah": null,
    "sert_prof": null,
    "link_pt": "/data_pt/QTA0QUFGRjgtNUY4MS00NzU2LUI5MTQtNzNEQ0ZFRDMzOTMy",
    "link_prodi": "/data_prodi/NTMzREFDMjEtRTkzMS00RTI2LUE4QzMtNjU0OUE4REQ4M0FG"
  }
}