{
  "datastatuskuliah": [
    {
      "id_smt": "20211",
      "sks_smt": 20,
      "nm_stat_mhs": "Aktif"
    },
    {
      "id_smt": "20212",
      "sks_smt": 20,
      "nm_stat_mhs": "Aktif"
    },
    {
      "id_smt": "20221",
      "sks_smt": 24,
      "nm_stat_mhs": "Aktif"
    },
    {
      "id_smt": "20222",
      "sks_smt": 24,
      "nm_stat_mhs": "Aktif"
    },
    {
      "id_smt": "20231",
      "sks_smt": 24,
      "nm_stat_mhs": "Aktif"
    }
  ],
  "datastudi": [
    {
      "kode_mk": "MKK313",
      "nm_mk": "GENETIKA",
      "sks_mk": 2,
      "id_smt": "20211",
      "nilai_huruf": null
    },
    {
      "kode_mk": "MKK213",
      "nm_mk": "BIOLOGI UMUM",
      "sks_mk": 3,
      "id_smt": "20211",
      "nilai_huruf": null
    },
    {
      "kode_mk": "MKK932",
      "nm_mk": "PENGANTAR ILMU EKONOMI",
      "sks_mk": 2,
      "id_smt": "20211",
      "nilai_huruf": null
    },
    {
      "kode_mk": "MKK312",
      "nm_mk": "BIOKIMIA UMUM",
      "sks_mk": 3,
      "id_smt": "20211",
      "nilai_huruf": null
    },
    {
      "kode_mk": "MKK933",
      "nm_mk": "ANATOMI & FISIOLOGI TERNAK",
      "sks_mk": 3,
      "id_smt": "20211",
      "nilai_huruf": null
    },
    {
      "kode_mk": "MKU005",
      "nm_mk": "*PENGANTAR ILMU PETERNAKAN",
      "sks_mk": 3,
      "id_smt": "20211",
      "nilai_huruf": null
    },
    {
      "kode_mk": "MPK114",
      "nm_mk": "BAHASA INDONESIA",
      "sks_mk": 2,
      "id_smt": "20211",
      "nilai_huruf": null
    },
    {
      "kode_mk": "MPK107",
      "nm_mk": "PENDIDIKAN KEWARGANEGARAAN",
      "sks_mk": 2,
      "id_smt": "20211",
      "nilai_huruf": null
    },
    {
      "kode_mk": "MKB935",
      "nm_mk": "ILMU PRODUKSI TERNAK POTONG/KERJA",
      "sks_mk": 2,
      "id_smt": "20212",
      "nilai_huruf": null
    },
    {
      "kode_mk": "MPB944",
      "nm_mk": "PERENCANAAN DAN EVALUASI USAHA PETERNAKAN",
      "sks_mk": 2,
      "id_smt": "20212",
      "nilai_huruf": null
    },
    {
      "kode_mk": "MKB611",
      "nm_mk": "ILMU REPRODUKSI TERNAK",
      "sks_mk": 3,
      "id_smt": "20212",
      "nilai_huruf": null
    },
    {
      "kode_mk": "MPK102",
      "nm_mk": "PENDIDIKAN AGAMA KRISTEN",
      "sks_mk": 2,
      "id_smt": "20212",
      "nilai_huruf": null
    },
    {
      "kode_mk": "MKB511",
      "nm_mk": "DASAR TEKNOLOGI HASIL TERNAK",
      "sks_mk": 3,
      "id_smt": "20212",
      "nilai_huruf": null
    },
    {
      "kode_mk": "MKB617",
      "nm_mk": "ILMU PEMULIAAN TERNAK",
      "sks_mk": 2,
      "id_smt": "20212",
      "nilai_huruf": null
    },
    {
      "kode_mk": "MKB415",
      "nm_mk": "ILMU NUTRISI TERNAK DASAR",
      "sks_mk": 2,
      "id_smt": "20212",
      "nilai_huruf": null
    },
    {
      "kode_mk": "MKB937",
      "nm_mk": "ILMU PRODUKSI TERNAK UNGGAS",
      "sks_mk": 2,
      "id_smt": "20212",
      "nilai_huruf": null
    },
    {
      "kode_mk": "MKB936",
      "nm_mk": "ILMU PRODUKSI TERNAK PERAH",
      "sks_mk": 2,
      "id_smt": "20212",
      "nilai_huruf": null
    },
    {
      "kode_mk": "MKK938",
      "nm_mk": "ILMU TANAMAN PAKAN TERNAK",
      "sks_mk": 3,
      "id_smt": "20221",
      "nilai_huruf": null
    },
    {
      "kode_mk": "MPB714",
      "nm_mk": "MANAJEMEN TERNAK PERAH",
      "sks_mk": 3,
      "id_smt": "20221",
      "nilai_huruf": null
    },
    {
      "kode_mk": "MPB712",
      "nm_mk": "MANAJEMEN TERNAK UNGGAS",
      "sks_mk": 3,
      "id_smt": "20221",
      "nilai_huruf": null
    },
    {
      "kode_mk": "MPB955",
      "nm_mk": "PENANGANAN PASCA PANEN HASIL TERNAK",
      "sks_mk": 2,
      "id_smt": "20221",
      "nilai_huruf": null
    },
    {
      "kode_mk": "MKB413",
      "nm_mk": "KEWIRAUSAHAAN",
      "sks_mk": 2,
      "id_smt": "20221",
      "nilai_huruf": null
    },
    {
      "kode_mk": "MPB713",
      "nm_mk": "MANAJEMEN TERNAK POTONG/KERJA",
      "sks_mk": 3,
      "id_smt": "20221",
      "nilai_huruf": null
    },
    {
      "kode_mk": "MPK117",
      "nm_mk": "JATIDIRI KANJURUHAN",
      "sks_mk": 2,
      "id_smt": "20221",
      "nilai_huruf": null
    },
    {
      "kode_mk": "MPB810",
      "nm_mk": "TEKNOLOGI REPRODUKSI TERNAK",
      "sks_mk": 3,
      "id_smt": "20221",
      "nilai_huruf": null
    },
    {
      "kode_mk": "MPB811",
      "nm_mk": "BAHAN PAKAN DAN FORMULASI RANSUM",
      "sks_mk": 3,
      "id_smt": "20221",
      "nilai_huruf": null
    },
    {
      "kode_mk": "MPB923",
      "nm_mk": "PEMASARAN DAN TATA NIAGA PETERNAKAN *",
      "sks_mk": 3,
      "id_smt": "20222",
      "nilai_huruf": null
    },
    {
      "kode_mk": "MPB829",
      "nm_mk": "TEKNOLOGI PENGOLAHAN HASIL TERNAK (Daging, Susu, Telur dan Ikutannya)",
      "sks_mk": 3,
      "id_smt": "20222",
      "nilai_huruf": null
    },
    {
      "kode_mk": "MPB822",
      "nm_mk": "SISTEM PERTANIAN TERPADU",
      "sks_mk": 3,
      "id_smt": "20222",
      "nilai_huruf": null
    },
    {
      "kode_mk": "MPB826",
      "nm_mk": "ILMU NUTRISI UNGGAS",
      "sks_mk": 3,
      "id_smt": "20222",
      "nilai_huruf": null
    },
    {
      "kode_mk": "MPB946",
      "nm_mk": "INSEMINASI BUATAN",
      "sks_mk": 3,
      "id_smt": "20222",
      "nilai_huruf": null
    },
    {
      "kode_mk": "MPK106",
      "nm_mk": "PENDIDIKAN PANCASILA",
      "sks_mk": 2,
      "id_smt": "20222",
      "nilai_huruf": null
    },
    {
      "kode_mk": "MKB710",
      "nm_mk": "ILMU KESEHATAN HEWAN",
      "sks_mk": 3,
      "id_smt": "20222",
      "nilai_huruf": null
    },
    {
      "kode_mk": "MPB950",
      "nm_mk": "RANCANGAN PERCOBAAN",
      "sks_mk": 2,
      "id_smt": "20222",
      "nilai_huruf": null
    },
    {
      "kode_mk": "MPK115",
      "nm_mk": "BAHASA INGGRIS",
      "sks_mk": 2,
      "id_smt": "20222",
      "nilai_huruf": null
    },
    {
      "kode_mk": "MKK934",
      "nm_mk": "PENYULUHAN & KOMUNIKASI",
      "sks_mk": 3,
      "id_smt": "20231",
      "nilai_huruf": null
    },
    {
      "kode_mk": "MPB954",
      "nm_mk": "PRAKTEK KEWIRAUSAHAAN",
      "sks_mk": 1,
      "id_smt": "20231",
      "nilai_huruf": null
    },
    {
      "kode_mk": "MPB947",
      "nm_mk": "AGRIBISNIS PETERNAKAN",
      "sks_mk": 3,
      "id_smt": "20231",
      "nilai_huruf": null
    },
    {
      "kode_mk": "MPB943",
      "nm_mk": "METODOLOGI PENELITIAN",
      "sks_mk": 2,
      "id_smt": "20231",
      "nilai_huruf": null
    },
    {
      "kode_mk": "MPB827",
      "nm_mk": "ILMU NUTRISI RUMINANSIA",
      "sks_mk": 3,
      "id_smt": "20231",
      "nilai_huruf": null
    },
    {
      "kode_mk": "MPB925",
      "nm_mk": "TEKNOLOGI PENGOLAHAN SUSU",
      "sks_mk": 3,
      "id_smt": "20231",
      "nilai_huruf": null
    },
    {
      "kode_mk": "MPB890",
      "nm_mk": "TEKNOLOGI PENGOLAHAN PAKAN",
      "sks_mk": 3,
      "id_smt": "20231",
      "nilai_huruf": null
    },
    {
      "kode_mk": "MPB814",
      "nm_mk": "PENGELOLAAN LIMBAH PETERNAKAN",
      "sks_mk": 3,
      "id_smt": "20231",
      "nilai_huruf": null
    },
    {
      "kode_mk": "MKK938",
      "nm_mk": "ILMU TANAMAN PAKAN TERNAK",
      "sks_mk": 3,
      "id_smt": "20231",
      "nilai_huruf": null
    }
  ],
  "dataumum": {
    "nm_pd": "YOSEA ARDANA",
    "jk": "L",
    "nipd": "210406030025",
    "namapt": "Universitas PGRI Kanjuruhan Malang",
    "namajenjang": "S1",
    "namaprodi": "Peternakan",
    "reg_pd": "CB2FE5EC-58C6-4C28-9F62-08125F3F49B1",
    "mulai_smt": "20211",
    "nm_jns_daftar": "Peserta didik baru",
    "nm_pt_asal": null,
    "nm_prodi_asal": null,
    "ket_keluar": null,
    "tgl_keluar": null,
    "no_seri_ijazah": null,
    "sert_prof": null,
    "link_pt": "/data_pt/MDYzNjBEQTgtOEY4Qy00MTY0LTk3ODktQjc1Mzc1NjM3RjY4",
    "link_prodi": "/data_prodi/QTA4ODMxOUEtRjcwQS00NjFCLUFBRTMtNzQ0ODgzMUM2MTdC"
  }
}