{
  "datastatuskuliah": [
    {
      "id_smt": "20131",
      "sks_smt": 22,
      "nm_stat_mhs": "Aktif"
    },
    {
      "id_smt": "20132",
      "sks_smt": 22,
      "nm_stat_mhs": "Aktif"
    },
    {
      "id_smt": "20141",
      "sks_smt": 18,
      "nm_stat_mhs": "Aktif"
    },
    {
      "id_smt": "20142",
      "sks_smt": null,
      "nm_stat_mhs": "Aktif"
    },
    {
      "id_smt": "20151",
      "sks_smt": 22,
      "nm_stat_mhs": "Aktif"
    },
    {
      "id_smt": "20152",
      "sks_smt": 18,
      "nm_stat_mhs": "Aktif"
    },
    {
      "id_smt": "20161",
      "sks_smt": 14,
      "nm_stat_mhs": "Aktif"
    },
    {
      "id_smt": "20162",
      "sks_smt": null,
      "nm_stat_mhs": "Cuti"
    },
    {
      "id_smt": "20171",
      "sks_smt": null,
      "nm_stat_mhs": "Non-Aktif                           "
    },
    {
      "id_smt": "20172",
      "sks_smt": null,
      "nm_stat_mhs": "Non-Aktif                           "
    },
    {
      "id_smt": "20181",
      "sks_smt": 18,
      "nm_stat_mhs": "Aktif"
    },
    {
      "id_smt": "20182",
      "sks_smt": 14,
      "nm_stat_mhs": "Aktif"
    }
  ],
  "datastudi": [
    {
      "kode_mk": "56376",
      "nm_mk": "PENDIDIKAN KEWARGANEGARAAN",
      "sks_mk": 2,
      "id_smt": "20131",
      "nilai_huruf": null
    },
    {
      "kode_mk": "56378",
      "nm_mk": "BAHASA INGGRIS I",
      "sks_mk": 2,
      "id_smt": "20131",
      "nilai_huruf": null
    },
    {
      "kode_mk": "56379",
      "nm_mk": "PENGANTAR BISNIS",
      "sks_mk": 3,
      "id_smt": "20131",
      "nilai_huruf": null
    },
    {
      "kode_mk": "56375",
      "nm_mk": "AL ISLAM DAN KEMUHAMMADIYAHAN I",
      "sks_mk": 1,
      "id_smt": "20131",
      "nilai_huruf": null
    },
    {
      "kode_mk": "56382",
      "nm_mk": "PENGANTAR EKONOMI MAKRO",
      "sks_mk": 3,
      "id_smt": "20131",
      "nilai_huruf": null
    },
    {
      "kode_mk": "56380",
      "nm_mk": "PENGANTAR AKUNTANSI",
      "sks_mk": 3,
      "id_smt": "20131",
      "nilai_huruf": null
    },
    {
      "kode_mk": "56381",
      "nm_mk": "PENGANTAR EKONOMI MIKRO",
      "sks_mk": 3,
      "id_smt": "20131",
      "nilai_huruf": null
    },
    {
      "kode_mk": "56377",
      "nm_mk": "IIMU SOSIAL DAN BUDAYA DASAR",
      "sks_mk": 2,
      "id_smt": "20131",
      "nilai_huruf": null
    },
    {
      "kode_mk": "56383",
      "nm_mk": "MATEMATIKA EKONOMI I",
      "sks_mk": 3,
      "id_smt": "20131",
      "nilai_huruf": null
    },
    {
      "kode_mk": "56386",
      "nm_mk": "BAHASA INGGRIS II",
      "sks_mk": 2,
      "id_smt": "20132",
      "nilai_huruf": null
    },
    {
      "kode_mk": "56391",
      "nm_mk": "MATEMATIKA EKONOMI II",
      "sks_mk": 3,
      "id_smt": "20132",
      "nilai_huruf": null
    },
    {
      "kode_mk": "56392",
      "nm_mk": "LEMBAGA KEUANGAN BANK DAN NON BANK",
      "sks_mk": 3,
      "id_smt": "20132",
      "nilai_huruf": null
    },
    {
      "kode_mk": "56387",
      "nm_mk": "SOSIOLOGI EKONOMI",
      "sks_mk": 2,
      "id_smt": "20132",
      "nilai_huruf": null
    },
    {
      "kode_mk": "56389",
      "nm_mk": "TEORI EKONOMI MIKRO I",
      "sks_mk": 3,
      "id_smt": "20132",
      "nilai_huruf": null
    },
    {
      "kode_mk": "56390",
      "nm_mk": "TEORI EKONOMI MAKRO I",
      "sks_mk": 3,
      "id_smt": "20132",
      "nilai_huruf": null
    },
    {
      "kode_mk": "56388",
      "nm_mk": "APLIKASI KOMPUTER UNTUK EKONOMI DAN BISN",
      "sks_mk": 3,
      "id_smt": "20132",
      "nilai_huruf": null
    },
    {
      "kode_mk": "56385",
      "nm_mk": "ILMU KEALAMAN DASAR",
      "sks_mk": 2,
      "id_smt": "20132",
      "nilai_huruf": null
    },
    {
      "kode_mk": "56384",
      "nm_mk": "AL ISLAM DAN KEMUHAMMADIYAHAN II",
      "sks_mk": 1,
      "id_smt": "20132",
      "nilai_huruf": null
    },
    {
      "kode_mk": "56397",
      "nm_mk": "MANAJEMEN KEUANGAN",
      "sks_mk": 3,
      "id_smt": "20141",
      "nilai_huruf": null
    },
    {
      "kode_mk": "56395",
      "nm_mk": "EKONOMI PEMBANGUNAN",
      "sks_mk": 3,
      "id_smt": "20141",
      "nilai_huruf": null
    },
    {
      "kode_mk": "56398",
      "nm_mk": "TEORI EKONOMI MIKRO II",
      "sks_mk": 3,
      "id_smt": "20141",
      "nilai_huruf": null
    },
    {
      "kode_mk": "56394",
      "nm_mk": "STATISTIK I",
      "sks_mk": 3,
      "id_smt": "20141",
      "nilai_huruf": null
    },
    {
      "kode_mk": "56396",
      "nm_mk": "EKONOMI INTERNASIONAL I",
      "sks_mk": 3,
      "id_smt": "20141",
      "nilai_huruf": null
    },
    {
      "kode_mk": "56399",
      "nm_mk": "TEORI EKONOMI MAKRO II",
      "sks_mk": 3,
      "id_smt": "20141",
      "nilai_huruf": null
    },
    {
      "kode_mk": "4201828170313",
      "nm_mk": "Studi Kelayakan Bisnis",
      "sks_mk": 3,
      "id_smt": "20142",
      "nilai_huruf": null
    },
    {
      "kode_mk": "4101804440313",
      "nm_mk": "Ekonomi Moneter",
      "sks_mk": 3,
      "id_smt": "20142",
      "nilai_huruf": null
    },
    {
      "kode_mk": "4201804240313",
      "nm_mk": "Ekonomi Internasional II",
      "sks_mk": 3,
      "id_smt": "20142",
      "nilai_huruf": null
    },
    {
      "kode_mk": "4101804600313",
      "nm_mk": "Ekonomi Publik I",
      "sks_mk": 3,
      "id_smt": "20142",
      "nilai_huruf": null
    },
    {
      "kode_mk": "4101804200313",
      "nm_mk": "Ekonomi Industri I",
      "sks_mk": 3,
      "id_smt": "20142",
      "nilai_huruf": null
    },
    {
      "kode_mk": "4201827330313",
      "nm_mk": "Statistik II",
      "sks_mk": 3,
      "id_smt": "20142",
      "nilai_huruf": null
    },
    {
      "kode_mk": "4201821350313",
      "nm_mk": "Perencanaan Pembangunan",
      "sks_mk": 3,
      "id_smt": "20151",
      "nilai_huruf": null
    },
    {
      "kode_mk": "2101804140313",
      "nm_mk": "Ekonometrika",
      "sks_mk": 3,
      "id_smt": "20151",
      "nilai_huruf": null
    },
    {
      "kode_mk": "4201804620313",
      "nm_mk": "Ekonomi Regional",
      "sks_mk": 3,
      "id_smt": "20151",
      "nilai_huruf": null
    },
    {
      "kode_mk": "4201804610313",
      "nm_mk": "Ekonomi Publik II",
      "sks_mk": 3,
      "id_smt": "20151",
      "nilai_huruf": null
    },
    {
      "kode_mk": "6101821090313",
      "nm_mk": "Perekonomian Indonesia",
      "sks_mk": 3,
      "id_smt": "20151",
      "nilai_huruf": null
    },
    {
      "kode_mk": "4201804660313",
      "nm_mk": "Ekonomi Sumber Daya Alam dan Lingkungan",
      "sks_mk": 3,
      "id_smt": "20151",
      "nilai_huruf": null
    },
    {
      "kode_mk": "1201800460113",
      "nm_mk": "Al Islam dan Kemuhammadiyahan III",
      "sks_mk": 1,
      "id_smt": "20151",
      "nilai_huruf": null
    },
    {
      "kode_mk": "4201804280313",
      "nm_mk": "Ekonomi Kependudukan",
      "sks_mk": 3,
      "id_smt": "20151",
      "nilai_huruf": null
    },
    {
      "kode_mk": "4201814800313",
      "nm_mk": "Masalah dan Kebijakan Pembangunan",
      "sks_mk": 3,
      "id_smt": "20152",
      "nilai_huruf": null
    },
    {
      "kode_mk": "4201804250313",
      "nm_mk": "Ekonomi Islam",
      "sks_mk": 3,
      "id_smt": "20152",
      "nilai_huruf": null
    },
    {
      "kode_mk": "1101825440313",
      "nm_mk": "Sejarah Pemikiran Ekonomi",
      "sks_mk": 3,
      "id_smt": "20152",
      "nilai_huruf": null
    },
    {
      "kode_mk": "4201804690313",
      "nm_mk": "Ekonomi Sumber Daya Manusia dan Ketenagakerjaan",
      "sks_mk": 3,
      "id_smt": "20152",
      "nilai_huruf": null
    },
    {
      "kode_mk": "2201813490313",
      "nm_mk": "Manajemen Keuangan Daerah",
      "sks_mk": 3,
      "id_smt": "20152",
      "nilai_huruf": null
    },
    {
      "kode_mk": "2201800730313",
      "nm_mk": "Analisa Kebijakan Publik",
      "sks_mk": 3,
      "id_smt": "20152",
      "nilai_huruf": null
    },
    {
      "kode_mk": "3101804470313",
      "nm_mk": "Ekonomi Pembangunan",
      "sks_mk": 3,
      "id_smt": "20161",
      "nilai_huruf": null
    },
    {
      "kode_mk": "1201801890213",
      "nm_mk": "Bahasa Indonesia",
      "sks_mk": 2,
      "id_smt": "20161",
      "nilai_huruf": null
    },
    {
      "kode_mk": "4201804280313",
      "nm_mk": "Ekonomi Kependudukan",
      "sks_mk": 3,
      "id_smt": "20161",
      "nilai_huruf": null
    },
    {
      "kode_mk": "2201825710313",
      "nm_mk": "Seminar Ekonomi Perencanaan Pembangunan",
      "sks_mk": 3,
      "id_smt": "20161",
      "nilai_huruf": null
    },
    {
      "kode_mk": "4201804820313",
      "nm_mk": "Ekspor-Impor",
      "sks_mk": 3,
      "id_smt": "20161",
      "nilai_huruf": null
    },
    {
      "kode_mk": "3101804470313",
      "nm_mk": "Ekonomi Pembangunan",
      "sks_mk": 3,
      "id_smt": "20181",
      "nilai_huruf": null
    },
    {
      "kode_mk": "4201804280313",
      "nm_mk": "Ekonomi Kependudukan",
      "sks_mk": 3,
      "id_smt": "20181",
      "nilai_huruf": null
    },
    {
      "kode_mk": "4201804820313",
      "nm_mk": "Ekspor-Impor",
      "sks_mk": 3,
      "id_smt": "20181",
      "nilai_huruf": null
    },
    {
      "kode_mk": "2201825710313",
      "nm_mk": "Seminar Ekonomi Perencanaan Pembangunan",
      "sks_mk": 3,
      "id_smt": "20181",
      "nilai_huruf": null
    },
    {
      "kode_mk": "2201818950313",
      "nm_mk": "Pengantar Akuntansi",
      "sks_mk": 3,
      "id_smt": "20181",
      "nilai_huruf": null
    },
    {
      "kode_mk": "4201804620313",
      "nm_mk": "Ekonomi Regional",
      "sks_mk": 3,
      "id_smt": "20181",
      "nilai_huruf": null
    },
    {
      "kode_mk": "4201811620313",
      "nm_mk": "Kewirausahaan",
      "sks_mk": 3,
      "id_smt": "20182",
      "nilai_huruf": null
    },
    {
      "kode_mk": "1201800470113",
      "nm_mk": "Al Islam dan Kemuhammadiyahan IV",
      "sks_mk": 1,
      "id_smt": "20182",
      "nilai_huruf": null
    },
    {
      "kode_mk": "1201802010213",
      "nm_mk": "Bahasa Inggris II",
      "sks_mk": 2,
      "id_smt": "20182",
      "nilai_huruf": null
    },
    {
      "kode_mk": "1201801890213",
      "nm_mk": "Bahasa Indonesia",
      "sks_mk": 2,
      "id_smt": "20182",
      "nilai_huruf": null
    },
    {
      "kode_mk": "3101829590313",
      "nm_mk": "Teori Ekonomi Mikro I",
      "sks_mk": 3,
      "id_smt": "20182",
      "nilai_huruf": null
    },
    {
      "kode_mk": "4201804250313",
      "nm_mk": "Ekonomi Islam",
      "sks_mk": 3,
      "id_smt": "20182",
      "nilai_huruf": null
    }
  ],
  "dataumum": {
    "nm_pd": "OKTO HENDRAWAN",
    "jk": "L",
    "nipd": "201310180311182   ",
    "namapt": "Universitas Muhammadiyah Malang",
    "namajenjang": "S1",
    "namaprodi": "Ekonomi Pembangunan",
    "reg_pd": "F235573D-D33E-48EA-9855-9985EB705DA0",
    "mulai_smt": "20131",
    "nm_jns_daftar": "Peserta didik baru",
    "nm_pt_asal": null,
    "nm_prodi_asal": null,
    "ket_keluar": "Mengundurkan diri",
    "tgl_keluar": "2019-08-26T00:00:00Z",
    "no_seri_ijazah": " ",
    "sert_prof": null,
    "link_pt": "/data_pt/NjM5OUQ3N0QtOEM1NS00REZBLTgwRjgtNzAwMjc1MjMwOTlF",
    "link_prodi": "/data_prodi/NDNDQzE2QTctNjlDNC00OTc4LUFFNDItNUNDOTU3QTU3MzM1"
  }
}