{
  "datastatuskuliah": [
    {
      "id_smt": "20221",
      "sks_smt": 20,
      "nm_stat_mhs": "Aktif"
    },
    {
      "id_smt": "20222",
      "sks_smt": 21,
      "nm_stat_mhs": "Aktif"
    },
    {
      "id_smt": "20231",
      "sks_smt": 16,
      "nm_stat_mhs": "Aktif"
    }
  ],
  "datastudi": [
    {
      "kode_mk": "MWU60103",
      "nm_mk": "PENDIDIKAN KEWARGANEGARAAN",
      "sks_mk": 2,
      "id_smt": "20221",
      "nilai_huruf": null
    },
    {
      "kode_mk": "AKT61127",
      "nm_mk": "PENGANTAR EKONOMI",
      "sks_mk": 3,
      "id_smt": "20221",
      "nilai_huruf": null
    },
    {
      "kode_mk": "AKT61126",
      "nm_mk": "PENGANTAR BISNIS",
      "sks_mk": 3,
      "id_smt": "20221",
      "nilai_huruf": null
    },
    {
      "kode_mk": "MWU60102",
      "nm_mk": "PANCASILA",
      "sks_mk": 2,
      "id_smt": "20221",
      "nilai_huruf": null
    },
    {
      "kode_mk": "FEB60101",
      "nm_mk": "TATA BAHASA INGGRIS DAN PENULISAN ILMIAH",
      "sks_mk": 2,
      "id_smt": "20221",
      "nilai_huruf": null
    },
    {
      "kode_mk": "AKT61102",
      "nm_mk": "PENGANTAR PERPAJAKAN",
      "sks_mk": 3,
      "id_smt": "20221",
      "nilai_huruf": null
    },
    {
      "kode_mk": "AKT61103",
      "nm_mk": "TEKNOLOGI INFORMASI DAN PERANCANGAN DATABASE",
      "sks_mk": 2,
      "id_smt": "20221",
      "nilai_huruf": null
    },
    {
      "kode_mk": "AKT61101",
      "nm_mk": "PENGANTAR AKUNTANSI",
      "sks_mk": 3,
      "id_smt": "20221",
      "nilai_huruf": null
    },
    {
      "kode_mk": "AKT62105",
      "nm_mk": "AKUNTANSI KEUANGAN INTERMEDIATE I",
      "sks_mk": 3,
      "id_smt": "20222",
      "nilai_huruf": null
    },
    {
      "kode_mk": "MWU60104",
      "nm_mk": "BAHASA INDONESIA",
      "sks_mk": 2,
      "id_smt": "20222",
      "nilai_huruf": null
    },
    {
      "kode_mk": "AKT62128",
      "nm_mk": "PENGANTAR MANAJEMEN",
      "sks_mk": 3,
      "id_smt": "20222",
      "nilai_huruf": null
    },
    {
      "kode_mk": "AKT62129",
      "nm_mk": "MATEMATIKA KEUANGAN BISNIS",
      "sks_mk": 3,
      "id_smt": "20222",
      "nilai_huruf": null
    },
    {
      "kode_mk": "AKT62104",
      "nm_mk": "PERPAJAKAN",
      "sks_mk": 3,
      "id_smt": "20222",
      "nilai_huruf": null
    },
    {
      "kode_mk": "AKT62130",
      "nm_mk": "PENGANTAR HUKUM BISNIS",
      "sks_mk": 2,
      "id_smt": "20222",
      "nilai_huruf": null
    },
    {
      "kode_mk": "AKT62106",
      "nm_mk": "AKUNTANSI BIAYA",
      "sks_mk": 3,
      "id_smt": "20222",
      "nilai_huruf": null
    },
    {
      "kode_mk": "MWU60101",
      "nm_mk": "AGAMA",
      "sks_mk": 2,
      "id_smt": "20222",
      "nilai_huruf": null
    },
    {
      "kode_mk": "AKT61109",
      "nm_mk": "AKUNTANSI MANAJEMEN",
      "sks_mk": 3,
      "id_smt": "20231",
      "nilai_huruf": null
    },
    {
      "kode_mk": "AKT61107",
      "nm_mk": "KEUANGAN NEGARA DAN DAERAH",
      "sks_mk": 3,
      "id_smt": "20231",
      "nilai_huruf": null
    },
    {
      "kode_mk": "AKT61131",
      "nm_mk": "MANAJEMEN KEUANGAN I",
      "sks_mk": 3,
      "id_smt": "20231",
      "nilai_huruf": null
    },
    {
      "kode_mk": "AKT61112",
      "nm_mk": "MANAJEMEN RISIKO",
      "sks_mk": 2,
      "id_smt": "20231",
      "nilai_huruf": null
    },
    {
      "kode_mk": "AKT61132",
      "nm_mk": "MANAJEMEN OPERASI",
      "sks_mk": 3,
      "id_smt": "20231",
      "nilai_huruf": null
    },
    {
      "kode_mk": "FEB60101",
      "nm_mk": "TATA BAHASA INGGRIS DAN PENULISAN ILMIAH",
      "sks_mk": 2,
      "id_smt": "20231",
      "nilai_huruf": null
    }
  ],
  "dataumum": {
    "nm_pd": "VANESA WULANDARI",
    "jk": "P",
    "nipd": "2210533080",
    "namapt": "Universitas Andalas",
    "namajenjang": "S1",
    "namaprodi": "Akuntansi",
    "reg_pd": "FD304E24-F585-480B-915B-5D120B375935",
    "mulai_smt": "20221",
    "nm_jns_daftar": "Peserta didik baru",
    "nm_pt_asal": null,
    "nm_prodi_asal": null,
    "ket_keluar": null,
    "tgl_keluar": null,
    "no_seri_ijazah": null,
    "sert_prof": null,
    "link_pt": "/data_pt/MTgwNENDNjYtQ0IxOS00RTkzLThCM0YtMUFGNzFBRDQ2OUZG",
    "link_prodi": "/data_prodi/QTE5QUYyRDMtRTEyRC00MDg2LTk2RkMtRTVBMTMyNkM2NEEw"
  }
}