{
  "datastatuskuliah": [
    {
      "id_smt": "20221",
      "sks_smt": 20,
      "nm_stat_mhs": "Aktif"
    },
    {
      "id_smt": "20222",
      "sks_smt": 20,
      "nm_stat_mhs": "Aktif"
    },
    {
      "id_smt": "20231",
      "sks_smt": 14,
      "nm_stat_mhs": "Aktif"
    }
  ],
  "datastudi": [
    {
      "kode_mk": "1203017290222",
      "nm_mk": "Pancasila",
      "sks_mk": 2,
      "id_smt": "20221",
      "nilai_huruf": null
    },
    {
      "kode_mk": "2203024020222",
      "nm_mk": "Psikologi",
      "sks_mk": 2,
      "id_smt": "20221",
      "nilai_huruf": null
    },
    {
      "kode_mk": "2203043020422",
      "nm_mk": "Ilmu Biomedik Dasar",
      "sks_mk": 4,
      "id_smt": "20221",
      "nilai_huruf": null
    },
    {
      "kode_mk": "1203058350222",
      "nm_mk": "Productive Skills of Foreign Languages for Specific Purpose",
      "sks_mk": 2,
      "id_smt": "20221",
      "nilai_huruf": null
    },
    {
      "kode_mk": "1203057260122",
      "nm_mk": "Keimanan dan Kemanusiaan",
      "sks_mk": 1,
      "id_smt": "20221",
      "nilai_huruf": null
    },
    {
      "kode_mk": "2203043050322",
      "nm_mk": "Keperawatan Dasar I",
      "sks_mk": 3,
      "id_smt": "20221",
      "nilai_huruf": null
    },
    {
      "kode_mk": "1203012200222",
      "nm_mk": "Komunikasi Keperawatan",
      "sks_mk": 2,
      "id_smt": "20221",
      "nilai_huruf": null
    },
    {
      "kode_mk": "2203012350222",
      "nm_mk": "Konsep Dasar Keperawatan",
      "sks_mk": 2,
      "id_smt": "20221",
      "nilai_huruf": null
    },
    {
      "kode_mk": "1203011590222",
      "nm_mk": "Kewarganegaraan",
      "sks_mk": 2,
      "id_smt": "20221",
      "nilai_huruf": null
    },
    {
      "kode_mk": "3203023720222",
      "nm_mk": "Promosi Kesehatan",
      "sks_mk": 2,
      "id_smt": "20222",
      "nilai_huruf": null
    },
    {
      "kode_mk": "2203017440222",
      "nm_mk": "Patofisiologi",
      "sks_mk": 2,
      "id_smt": "20222",
      "nilai_huruf": null
    },
    {
      "kode_mk": "3203043060222",
      "nm_mk": "Keperawatan Dasar II",
      "sks_mk": 2,
      "id_smt": "20222",
      "nilai_huruf": null
    },
    {
      "kode_mk": "2203005750322",
      "nm_mk": "Farmakologi",
      "sks_mk": 3,
      "id_smt": "20222",
      "nilai_huruf": null
    },
    {
      "kode_mk": "1203058360222",
      "nm_mk": "English Proficiency Test Preparation Course",
      "sks_mk": 2,
      "id_smt": "20222",
      "nilai_huruf": null
    },
    {
      "kode_mk": "3203003950222",
      "nm_mk": "Dokumentasi Keperawatan",
      "sks_mk": 2,
      "id_smt": "20222",
      "nilai_huruf": null
    },
    {
      "kode_mk": "1203057270122",
      "nm_mk": "Ibadah dan Mu'amalah",
      "sks_mk": 1,
      "id_smt": "20222",
      "nilai_huruf": null
    },
    {
      "kode_mk": "3203043130222",
      "nm_mk": "Antropologi Kesehatan",
      "sks_mk": 2,
      "id_smt": "20222",
      "nilai_huruf": null
    },
    {
      "kode_mk": "2203059570222",
      "nm_mk": "Metodologi Keperawatan",
      "sks_mk": 2,
      "id_smt": "20222",
      "nilai_huruf": null
    },
    {
      "kode_mk": "1203001890222",
      "nm_mk": "Bahasa Indonesia",
      "sks_mk": 2,
      "id_smt": "20222",
      "nilai_huruf": null
    },
    {
      "kode_mk": "3203043070222",
      "nm_mk": "Gizi dan Diet",
      "sks_mk": 2,
      "id_smt": "20231",
      "nilai_huruf": null
    },
    {
      "kode_mk": "2203059580222",
      "nm_mk": "Metodologi Sistem Informasi",
      "sks_mk": 2,
      "id_smt": "20231",
      "nilai_huruf": null
    },
    {
      "kode_mk": "3203010820222",
      "nm_mk": "Kepemimpinan dan Manajemen Keperawatan",
      "sks_mk": 2,
      "id_smt": "20231",
      "nilai_huruf": null
    },
    {
      "kode_mk": "2203005380222",
      "nm_mk": "Etika Keperawatan dan Hukum Kesehatan",
      "sks_mk": 2,
      "id_smt": "20231",
      "nilai_huruf": null
    },
    {
      "kode_mk": "3203011210322",
      "nm_mk": "Keperawatan Medikal Bedah I",
      "sks_mk": 3,
      "id_smt": "20231",
      "nilai_huruf": null
    },
    {
      "kode_mk": "3203043100322",
      "nm_mk": "Praktik Klinik Keperawatan Dasar",
      "sks_mk": 3,
      "id_smt": "20231",
      "nilai_huruf": null
    }
  ],
  "dataumum": {
    "nm_pd": "LATIF IKSANDI",
    "jk": "L",
    "nipd": "202210300511033",
    "namapt": "Universitas Muhammadiyah Malang",
    "namajenjang": "D3",
    "namaprodi": "Keperawatan",
    "reg_pd": "25490210-80BD-4ECB-9CC9-7DDE7445662F",
    "mulai_smt": "20221",
    "nm_jns_daftar": "Peserta didik baru",
    "nm_pt_asal": null,
    "nm_prodi_asal": null,
    "ket_keluar": null,
    "tgl_keluar": null,
    "no_seri_ijazah": null,
    "sert_prof": null,
    "link_pt": "/data_pt/NjM5OUQ3N0QtOEM1NS00REZBLTgwRjgtNzAwMjc1MjMwOTlF",
    "link_prodi": "/data_prodi/QzI3QjkyQ0UtQTVBNy00MzE3LThEN0EtOEZERUIxNjE0QTI4"
  }
}