{
  "datastatuskuliah": [
    {
      "id_smt": "20181",
      "sks_smt": 20,
      "nm_stat_mhs": "Aktif"
    },
    {
      "id_smt": "20182",
      "sks_smt": 20,
      "nm_stat_mhs": "Aktif"
    },
    {
      "id_smt": "20191",
      "sks_smt": 21,
      "nm_stat_mhs": "Aktif"
    },
    {
      "id_smt": "20192",
      "sks_smt": 20,
      "nm_stat_mhs": "Aktif"
    },
    {
      "id_smt": "20201",
      "sks_smt": 0,
      "nm_stat_mhs": "Non-Aktif                           "
    }
  ],
  "datastudi": [
    {
      "kode_mk": "DOK116",
      "nm_mk": "BIOMEDIK 1 ( SEL, TISSUE DAN ORGAN)",
      "sks_mk": 4,
      "id_smt": "20181",
      "nilai_huruf": null
    },
    {
      "kode_mk": "DOK136",
      "nm_mk": "KOMUNIKASI EFEKTIF DOKTER",
      "sks_mk": 2,
      "id_smt": "20181",
      "nilai_huruf": null
    },
    {
      "kode_mk": "DOK115",
      "nm_mk": "KETRAMPILAN BELAJAR DAN BERFIKIR KRITIS",
      "sks_mk": 3,
      "id_smt": "20181",
      "nilai_huruf": null
    },
    {
      "kode_mk": "DOK117",
      "nm_mk": "BIOMEDIK 2 (BIOLOGI MOLEKULER DAN GENETIK)",
      "sks_mk": 4,
      "id_smt": "20181",
      "nilai_huruf": null
    },
    {
      "kode_mk": "DOK118",
      "nm_mk": "BIOMEDIK 3 (DASAR DIAGNOSTIK DAN TERAPI)",
      "sks_mk": 3,
      "id_smt": "20181",
      "nilai_huruf": null
    },
    {
      "kode_mk": "UAI102",
      "nm_mk": "PENDIDIKAN AGAMA ISLAM 1",
      "sks_mk": 2,
      "id_smt": "20181",
      "nilai_huruf": null
    },
    {
      "kode_mk": "DOK129",
      "nm_mk": "HUMANIORA 1 (PANCASILA DAN KEWARGANEGARAAN)",
      "sks_mk": 2,
      "id_smt": "20181",
      "nilai_huruf": null
    },
    {
      "kode_mk": "DOK204",
      "nm_mk": "BAHASA INDONESIA",
      "sks_mk": 2,
      "id_smt": "20182",
      "nilai_huruf": null
    },
    {
      "kode_mk": "DOK237",
      "nm_mk": "ILMU KESEHATAN MASYARAKAT DAN KOMUNITAS 1",
      "sks_mk": 2,
      "id_smt": "20182",
      "nilai_huruf": null
    },
    {
      "kode_mk": "DOK230",
      "nm_mk": "SYSTEM DERMATOMUSCULOSKELETAL",
      "sks_mk": 7,
      "id_smt": "20182",
      "nilai_huruf": null
    },
    {
      "kode_mk": "DOK232",
      "nm_mk": "HUMANIORA 2 (ETIKA KEDOKTERAN)",
      "sks_mk": 2,
      "id_smt": "20182",
      "nilai_huruf": null
    },
    {
      "kode_mk": "DOK214",
      "nm_mk": "System Endokrin dan Metabolisme",
      "sks_mk": 7,
      "id_smt": "20182",
      "nilai_huruf": null
    },
    {
      "kode_mk": "UAI 203",
      "nm_mk": "PENDIDIKAN AGAMA ISLAM 2 (PESANTREN MAHASISWA BARU)",
      "sks_mk": 0,
      "id_smt": "20182",
      "nilai_huruf": null
    },
    {
      "kode_mk": "DOK341",
      "nm_mk": "EPIDEMIOLOGI",
      "sks_mk": 2,
      "id_smt": "20191",
      "nilai_huruf": null
    },
    {
      "kode_mk": "UAI303",
      "nm_mk": "PENDIDIKAN AGAMA ISLAM 3",
      "sks_mk": 1,
      "id_smt": "20191",
      "nilai_huruf": null
    },
    {
      "kode_mk": "DOK316",
      "nm_mk": "SYSTEM NEUROBEHAVIOUR",
      "sks_mk": 7,
      "id_smt": "20191",
      "nilai_huruf": null
    },
    {
      "kode_mk": "DOK318",
      "nm_mk": "SYSTEM IMUNOLOGI",
      "sks_mk": 3,
      "id_smt": "20191",
      "nilai_huruf": null
    },
    {
      "kode_mk": "DOK304",
      "nm_mk": "BAHASA INGGRIS",
      "sks_mk": 2,
      "id_smt": "20191",
      "nilai_huruf": null
    },
    {
      "kode_mk": "DOK331",
      "nm_mk": "HUMANIORA 3 (SOSIOLOGI DAN ANTHROPOLOGI KEDOKTERAN)",
      "sks_mk": 2,
      "id_smt": "20191",
      "nilai_huruf": null
    },
    {
      "kode_mk": "DOK317",
      "nm_mk": "SYSTEM HEMATOLOGI DAN ONKOLOGI",
      "sks_mk": 4,
      "id_smt": "20191",
      "nilai_huruf": null
    },
    {
      "kode_mk": "DOK420",
      "nm_mk": "SYSTEM KARDIOVASKULER",
      "sks_mk": 7,
      "id_smt": "20192",
      "nilai_huruf": null
    },
    {
      "kode_mk": "DOK442",
      "nm_mk": "BIOSTATISTIK",
      "sks_mk": 2,
      "id_smt": "20192",
      "nilai_huruf": null
    },
    {
      "kode_mk": "DOK432",
      "nm_mk": "HUMANIORA 4 (HUKUM KESEHATAN)",
      "sks_mk": 1,
      "id_smt": "20192",
      "nilai_huruf": null
    },
    {
      "kode_mk": "DOK419",
      "nm_mk": "SYSTEM RESPIRASI",
      "sks_mk": 7,
      "id_smt": "20192",
      "nilai_huruf": null
    },
    {
      "kode_mk": "UAI404",
      "nm_mk": "PENDIDIKAN AGAMA ISLAM 4",
      "sks_mk": 1,
      "id_smt": "20192",
      "nilai_huruf": null
    },
    {
      "kode_mk": "DOK438",
      "nm_mk": "ILMU KESEHATAN MASYARAKAT DAN KOMUNITAS 2",
      "sks_mk": 2,
      "id_smt": "20192",
      "nilai_huruf": null
    }
  ],
  "dataumum": {
    "nm_pd": "FALMAHYRA KEZIA AZ-ZAHRA",
    "jk": "P",
    "nipd": "10100118001",
    "namapt": "Universitas Islam Bandung",
    "namajenjang": "S1",
    "namaprodi": "Kedokteran",
    "reg_pd": "22511DD5-0E66-4CF4-89C0-4E5A71A8CC84",
    "mulai_smt": "20181",
    "nm_jns_daftar": "Peserta didik baru",
    "nm_pt_asal": null,
    "nm_prodi_asal": null,
    "ket_keluar": "Mutasi",
    "tgl_keluar": "2020-08-26T00:00:00Z",
    "no_seri_ijazah": null,
    "sert_prof": null,
    "link_pt": "/data_pt/M0YxNDgzRjctMjU2RC00QUNFLThDNjAtRDVBRTIwMjFENERF",
    "link_prodi": "/data_prodi/NzAxRUVFQ0UtMDY3Ny00QUMyLThERDItOUJBQzk1MTU0NDQ3"
  }
}