{
  "datastatuskuliah": [
    {
      "id_smt": "20151",
      "sks_smt": 12,
      "nm_stat_mhs": "Aktif"
    },
    {
      "id_smt": "20152",
      "sks_smt": 15,
      "nm_stat_mhs": "Aktif"
    },
    {
      "id_smt": "20161",
      "sks_smt": 13,
      "nm_stat_mhs": "Aktif"
    }
  ],
  "datastudi": [
    {
      "kode_mk": "C1MSDM",
      "nm_mk": "MANAJEMEN SDM",
      "sks_mk": 3,
      "id_smt": "20151",
      "nilai_huruf": null
    },
    {
      "kode_mk": "C1MPAS",
      "nm_mk": "MANAJEMEN PEMASARAN SYARIAH",
      "sks_mk": 3,
      "id_smt": "20151",
      "nilai_huruf": null
    },
    {
      "kode_mk": "C1LEKB",
      "nm_mk": "LINGKUNGAN EKONOMI BISNIS SYARIAH",
      "sks_mk": 3,
      "id_smt": "20151",
      "nilai_huruf": null
    },
    {
      "kode_mk": "C1MOPE",
      "nm_mk": "MANAJEMEN OPERASI",
      "sks_mk": 3,
      "id_smt": "20151",
      "nilai_huruf": null
    },
    {
      "kode_mk": "C2MPEN",
      "nm_mk": "METODOLOGI PENELITIANBISNIS SYARIAH",
      "sks_mk": 3,
      "id_smt": "20152",
      "nilai_huruf": null
    },
    {
      "kode_mk": "C2EMAN",
      "nm_mk": "EKONOMI MANAJERIAL SYARIAH",
      "sks_mk": 3,
      "id_smt": "20152",
      "nilai_huruf": null
    },
    {
      "kode_mk": "C2MKEU",
      "nm_mk": "MANAJEMEN KEUANGAN SYARIAH",
      "sks_mk": 3,
      "id_smt": "20152",
      "nilai_huruf": null
    },
    {
      "kode_mk": "C2MSTR",
      "nm_mk": "MANAJEMEN STRATEGIK",
      "sks_mk": 3,
      "id_smt": "20152",
      "nilai_huruf": null
    },
    {
      "kode_mk": "C4FILM",
      "nm_mk": "FILSAFAT ILMU",
      "sks_mk": 3,
      "id_smt": "20152",
      "nilai_huruf": null
    },
    {
      "kode_mk": "E3PSFMU",
      "nm_mk": "FIQIH MUAMALAH",
      "sks_mk": 3,
      "id_smt": "20161",
      "nilai_huruf": null
    },
    {
      "kode_mk": "E3PSPKS",
      "nm_mk": "PERILAKU KONSUMEN SYARIAH",
      "sks_mk": 3,
      "id_smt": "20161",
      "nilai_huruf": null
    },
    {
      "kode_mk": "C4TES",
      "nm_mk": "TESIS",
      "sks_mk": 6,
      "id_smt": "20161",
      "nilai_huruf": null
    },
    {
      "kode_mk": "C4ETBI",
      "nm_mk": "ETIKA BISNIS ISLAM",
      "sks_mk": 1,
      "id_smt": "20161",
      "nilai_huruf": null
    },
    {
      "kode_mk": "E3KUKOB",
      "nm_mk": "KOMUNIKASI BISNIS ISLAM",
      "sks_mk": 3,
      "id_smt": "20161",
      "nilai_huruf": null
    },
    {
      "kode_mk": "E3PSPLBS",
      "nm_mk": "PEMASARAN GLOBAL",
      "sks_mk": 3,
      "id_smt": "20161",
      "nilai_huruf": null
    }
  ],
  "dataumum": {
    "nm_pd": "KAMBALI",
    "jk": "L",
    "nipd": "2015P20006",
    "namapt": "Universitas Islam Batik",
    "namajenjang": "S2",
    "namaprodi": "Manajemen",
    "reg_pd": "AD5ADF6B-BB2B-4932-90D3-07D966A11E28",
    "mulai_smt": "20151",
    "nm_jns_daftar": "Peserta didik baru",
    "nm_pt_asal": null,
    "nm_prodi_asal": null,
    "ket_keluar": "Lulus",
    "tgl_keluar": "2017-03-14T00:00:00Z",
    "no_seri_ijazah": "2017050584 - D",
    "sert_prof": null,
    "link_pt": "/data_pt/MzFBNDVBOUQtQURFNC00NTQ2LThEOEItODc0ODgzQkZEMDMx",
    "link_prodi": "/data_prodi/M0FBMTlFNzgtQTA5Ni00NkUzLUJEMzQtMzUyQzU2MTY0QkI4"
  }
}