{
  "datastatuskuliah": [
    {
      "id_smt": "20161",
      "sks_smt": 20,
      "nm_stat_mhs": "Aktif"
    },
    {
      "id_smt": "20162",
      "sks_smt": 24,
      "nm_stat_mhs": "Aktif"
    },
    {
      "id_smt": "20171",
      "sks_smt": 21,
      "nm_stat_mhs": "Aktif"
    },
    {
      "id_smt": "20172",
      "sks_smt": 18,
      "nm_stat_mhs": "Aktif"
    },
    {
      "id_smt": "20181",
      "sks_smt": 22,
      "nm_stat_mhs": "Aktif"
    },
    {
      "id_smt": "20182",
      "sks_smt": 17,
      "nm_stat_mhs": "Aktif"
    },
    {
      "id_smt": "20191",
      "sks_smt": 17,
      "nm_stat_mhs": "Aktif"
    },
    {
      "id_smt": "20192",
      "sks_smt": 6,
      "nm_stat_mhs": "Aktif"
    },
    {
      "id_smt": "20201",
      "sks_smt": 6,
      "nm_stat_mhs": "Aktif"
    }
  ],
  "datastudi": [
    {
      "kode_mk": "15P00713",
      "nm_mk": "Kode Etik Psikologi",
      "sks_mk": 2,
      "id_smt": "20161",
      "nilai_huruf": null
    },
    {
      "kode_mk": "15F00026",
      "nm_mk": "Ilmu Pendidikan",
      "sks_mk": 2,
      "id_smt": "20161",
      "nilai_huruf": null
    },
    {
      "kode_mk": "15F00027",
      "nm_mk": "Pendidikan Karakter",
      "sks_mk": 2,
      "id_smt": "20161",
      "nilai_huruf": null
    },
    {
      "kode_mk": "15U00008",
      "nm_mk": "Pendidikan Kewarganegaraan",
      "sks_mk": 2,
      "id_smt": "20161",
      "nilai_huruf": null
    },
    {
      "kode_mk": "15U00010",
      "nm_mk": "Bahasa Inggris",
      "sks_mk": 2,
      "id_smt": "20161",
      "nilai_huruf": null
    },
    {
      "kode_mk": "15P00711",
      "nm_mk": "Sejarah dan Aliran Psikologi",
      "sks_mk": 3,
      "id_smt": "20161",
      "nilai_huruf": null
    },
    {
      "kode_mk": "15P00712",
      "nm_mk": "Perkembangan Anak dan Remaja",
      "sks_mk": 3,
      "id_smt": "20161",
      "nilai_huruf": null
    },
    {
      "kode_mk": "15U00012",
      "nm_mk": "Pendidikan Konservasi",
      "sks_mk": 2,
      "id_smt": "20161",
      "nilai_huruf": null
    },
    {
      "kode_mk": "15U00001",
      "nm_mk": "Pendidikan Agama Islam",
      "sks_mk": 2,
      "id_smt": "20161",
      "nilai_huruf": null
    },
    {
      "kode_mk": "15P00716",
      "nm_mk": "Perkembangan Dewasa dan Lanjut Usia",
      "sks_mk": 3,
      "id_smt": "20162",
      "nilai_huruf": null
    },
    {
      "kode_mk": "15U00007",
      "nm_mk": "Pendidikan Pancasila",
      "sks_mk": 2,
      "id_smt": "20162",
      "nilai_huruf": null
    },
    {
      "kode_mk": "15P00725",
      "nm_mk": "Psikologi Industri dan Organisasi",
      "sks_mk": 4,
      "id_smt": "20162",
      "nilai_huruf": null
    },
    {
      "kode_mk": "15P00718",
      "nm_mk": "Psikologi Sosial",
      "sks_mk": 4,
      "id_smt": "20162",
      "nilai_huruf": null
    },
    {
      "kode_mk": "15P00717",
      "nm_mk": "Psikologi Kognitif",
      "sks_mk": 2,
      "id_smt": "20162",
      "nilai_huruf": null
    },
    {
      "kode_mk": "15U00009",
      "nm_mk": "Bahasa Indonesia",
      "sks_mk": 2,
      "id_smt": "20162",
      "nilai_huruf": null
    },
    {
      "kode_mk": "15P00714",
      "nm_mk": "Biopsikologi",
      "sks_mk": 4,
      "id_smt": "20162",
      "nilai_huruf": null
    },
    {
      "kode_mk": "15P00715",
      "nm_mk": "Teori-Teori Belajar",
      "sks_mk": 3,
      "id_smt": "20162",
      "nilai_huruf": null
    },
    {
      "kode_mk": "15P00719",
      "nm_mk": "Psikologi Abnormal",
      "sks_mk": 3,
      "id_smt": "20171",
      "nilai_huruf": null
    },
    {
      "kode_mk": "15U00011",
      "nm_mk": "Kewirausahaan",
      "sks_mk": 2,
      "id_smt": "20171",
      "nilai_huruf": null
    },
    {
      "kode_mk": "15P00720",
      "nm_mk": "Statistika Dasar dan Metodologi Penelitian Survey",
      "sks_mk": 4,
      "id_smt": "20171",
      "nilai_huruf": null
    },
    {
      "kode_mk": "15P00721",
      "nm_mk": "Psikodiagnostika Dasar",
      "sks_mk": 4,
      "id_smt": "20171",
      "nilai_huruf": null
    },
    {
      "kode_mk": "15P00722",
      "nm_mk": "Teori Kepribadian Psikodinamika dan Neo-Freudian",
      "sks_mk": 3,
      "id_smt": "20171",
      "nilai_huruf": null
    },
    {
      "kode_mk": "15P00736",
      "nm_mk": "Psikologi Sekolah",
      "sks_mk": 3,
      "id_smt": "20171",
      "nilai_huruf": null
    },
    {
      "kode_mk": "15P00723",
      "nm_mk": "Psikologi Komunikasi",
      "sks_mk": 2,
      "id_smt": "20171",
      "nilai_huruf": null
    },
    {
      "kode_mk": "15P00727",
      "nm_mk": "Konsep Dasar Psikometri dan Penyusunan Alat Ukur Psikologi",
      "sks_mk": 4,
      "id_smt": "20172",
      "nilai_huruf": null
    },
    {
      "kode_mk": "15P00726",
      "nm_mk": "Statistika Inferensial dan Metode Penelitian Eksperimen",
      "sks_mk": 4,
      "id_smt": "20172",
      "nilai_huruf": null
    },
    {
      "kode_mk": "15P00739",
      "nm_mk": "Patologi Sosial",
      "sks_mk": 2,
      "id_smt": "20172",
      "nilai_huruf": null
    },
    {
      "kode_mk": "15P00729",
      "nm_mk": "Teori Kepribadian Behavioristik, Humanistik dan Teori Trait",
      "sks_mk": 3,
      "id_smt": "20172",
      "nilai_huruf": null
    },
    {
      "kode_mk": "15P00727",
      "nm_mk": "Konsep Dasar Psikometri dan Penyusunan Alat Ukur Psikologi",
      "sks_mk": 4,
      "id_smt": "20172",
      "nilai_huruf": null
    },
    {
      "kode_mk": "15P00730",
      "nm_mk": "Pengembangan Diri dan Karir",
      "sks_mk": 2,
      "id_smt": "20172",
      "nilai_huruf": null
    },
    {
      "kode_mk": "15P00728",
      "nm_mk": "Dasar-dasar Konseling",
      "sks_mk": 3,
      "id_smt": "20172",
      "nilai_huruf": null
    },
    {
      "kode_mk": "15U00021",
      "nm_mk": "Skripsi",
      "sks_mk": 6,
      "id_smt": "20191",
      "nilai_huruf": null
    },
    {
      "kode_mk": "15U00020",
      "nm_mk": "Praktik Kerja Lapangan",
      "sks_mk": 4,
      "id_smt": "20191",
      "nilai_huruf": null
    },
    {
      "kode_mk": "15P00742",
      "nm_mk": "Isu Psikologi Pendidikan",
      "sks_mk": 3,
      "id_smt": "20191",
      "nilai_huruf": null
    },
    {
      "kode_mk": "15U00019",
      "nm_mk": "Kuliah Kerja Nyata",
      "sks_mk": 4,
      "id_smt": "20191",
      "nilai_huruf": null
    },
    {
      "kode_mk": "15U00021",
      "nm_mk": "Skripsi",
      "sks_mk": 6,
      "id_smt": "20192",
      "nilai_huruf": null
    },
    {
      "kode_mk": "15U00021",
      "nm_mk": "Skripsi",
      "sks_mk": 6,
      "id_smt": "20201",
      "nilai_huruf": null
    }
  ],
  "dataumum": {
    "nm_pd": "INTEN LANJAR KAMULYAN",
    "jk": "P",
    "nipd": "1511416055",
    "namapt": "Universitas Negeri Semarang",
    "namajenjang": "S1",
    "namaprodi": "Psikologi",
    "reg_pd": "616B3D89-372C-4302-81EC-F48B47E87FAA",
    "mulai_smt": "20161",
    "nm_jns_daftar": "Peserta didik baru",
    "nm_pt_asal": null,
    "nm_prodi_asal": null,
    "ket_keluar": "Lulus",
    "tgl_keluar": "2020-09-01T00:00:00Z",
    "no_seri_ijazah": "732012020000186",
    "sert_prof": null,
    "link_pt": "/data_pt/QTU4NTg4QTgtMEY1Mi00RDRELThBQTgtRjgzMjc4QTU2NTU5",
    "link_prodi": "/data_prodi/RUJERUYyOTAtMUFFNC00RDNFLThBNkUtOUUyRTdCMDhBNTFE"
  }
}