{
  "datastatuskuliah": [],
  "datastudi": [],
  "dataumum": {
    "nm_pd": "ANI KRISDIANA",
    "jk": "P",
    "nipd": "98220118          ",
    "namapt": "Universitas Merdeka Malang",
    "namajenjang": "S1",
    "namaprodi": "Manajemen",
    "reg_pd": "53EAA950-48FC-4622-A886-2CF41D6ABFD4",
    "mulai_smt": "19981",
    "nm_jns_daftar": "Peserta didik baru",
    "nm_pt_asal": null,
    "nm_prodi_asal": null,
    "ket_keluar": "Lulus",
    "tgl_keluar": "2002-09-07T00:00:00Z",
    "no_seri_ijazah": "22-0131/UM/II/2002",
    "sert_prof": null,
    "link_pt": "/data_pt/ODRCMjU0NTUtNkVGQi00RjdDLUIxQjEtRTFEMUNBNEM2QUM4",
    "link_prodi": "/data_prodi/QjhCNzhBRUItQ0Y5QS00NkE2LTk0OUItNjJEN0UxOEU4MTg5"
  }
}