{
  "datastatuskuliah": [
    {
      "id_smt": "20052",
      "sks_smt": 14,
      "nm_stat_mhs": "Aktif"
    },
    {
      "id_smt": "20061",
      "sks_smt": 12,
      "nm_stat_mhs": "Aktif"
    },
    {
      "id_smt": "20062",
      "sks_smt": 12,
      "nm_stat_mhs": "Aktif"
    },
    {
      "id_smt": "20071",
      "sks_smt": 0,
      "nm_stat_mhs": "Aktif"
    }
  ],
  "datastudi": [],
  "dataumum": {
    "nm_pd": "BUDIMAN HADI",
    "jk": "L",
    "nipd": "06750002          ",
    "namapt": "Universitas Merdeka Malang",
    "namajenjang": "S2",
    "namaprodi": "Manajemen",
    "reg_pd": "F48864EC-F62D-4A29-A8DC-D03A6A470188",
    "mulai_smt": "20061",
    "nm_jns_daftar": "Peserta didik baru",
    "nm_pt_asal": null,
    "nm_prodi_asal": null,
    "ket_keluar": "Lainnya",
    "tgl_keluar": "2007-01-01T00:00:00Z",
    "no_seri_ijazah": null,
    "sert_prof": null,
    "link_pt": "/data_pt/ODRCMjU0NTUtNkVGQi00RjdDLUIxQjEtRTFEMUNBNEM2QUM4",
    "link_prodi": "/data_prodi/OTQ0MDgwRTktMjVDNC00OUJDLTgyQ0UtNDJFQjM4MDQ1NTI4"
  }
}