{
  "datastatuskuliah": [
    {
      "id_smt": "20021",
      "sks_smt": 6,
      "nm_stat_mhs": "Aktif"
    },
    {
      "id_smt": "20031",
      "sks_smt": 0,
      "nm_stat_mhs": "Aktif"
    },
    {
      "id_smt": "20041",
      "sks_smt": 4,
      "nm_stat_mhs": "Lulus"
    }
  ],
  "datastudi": [],
  "dataumum": {
    "nm_pd": "YESSI INDAH KUSUMANINGRUM",
    "jk": "P",
    "nipd": "98400194          ",
    "namapt": "Universitas Muhammadiyah Malang",
    "namajenjang": "S1",
    "namaprodi": "Hukum",
    "reg_pd": "E1354388-F6E9-480B-B2DD-2D243D7CA150",
    "mulai_smt": "19981",
    "nm_jns_daftar": "Peserta didik baru",
    "nm_pt_asal": null,
    "nm_prodi_asal": null,
    "ket_keluar": "Lulus",
    "tgl_keluar": "2004-12-24T00:00:00Z",
    "no_seri_ijazah": "05.1.40.01630",
    "sert_prof": null,
    "link_pt": "/data_pt/NjM5OUQ3N0QtOEM1NS00REZBLTgwRjgtNzAwMjc1MjMwOTlF",
    "link_prodi": "/data_prodi/MTNCOEZCQUItNkQzOS00REIxLTk0OEItMzNFRDA1RjUzOEI1"
  }
}